[
    {
        "name": "C12(WMA01)MS",
        "id": 1,
        "url": "https://files.gitbook.com/v0/b/gitbook-x-prod.appspot.com/o/spaces%2FwFIlpgG4w2DGcN1UNMAZ%2Fuploads%2FpY6jRZ9FGy6H7GSQETRS%2FWMA01_01_msc_20150305.pdf?alt=media&token=7d62e64f-ec98-4e45-bcae-b35693e3fabd"
    },
    {
        "name": "C34(WMA02)MS",
        "id": 2,
        "url": "https://files.gitbook.com/v0/b/gitbook-x-prod.appspot.com/o/spaces%2FwFIlpgG4w2DGcN1UNMAZ%2Fuploads%2Ffpy70JyvPmVIHONHz5ek%2FWMA02_01_msc_20150305.pdf?alt=media&token=1a1d0c52-4d1b-4ecb-88b8-47a014703651"
    },
    {
        "name": "D1(WDM01)MS",
        "id": 3,
        "url": "https://files.gitbook.com/v0/b/gitbook-x-prod.appspot.com/o/spaces%2FwFIlpgG4w2DGcN1UNMAZ%2Fuploads%2F17IC60t76ch3HXZsSGX8%2FWDM01_01_msc_20150305.pdf?alt=media&token=9d7c1a33-05a9-4689-bf92-1de179831c29"
    },
    {
        "name": "F1(WFM01)MS",
        "id": 4,
        "url": "https://files.gitbook.com/v0/b/gitbook-x-prod.appspot.com/o/spaces%2FwFIlpgG4w2DGcN1UNMAZ%2Fuploads%2FzhTsU6RV9fItwLerFKKo%2FWFM01_01_msc_20150305.pdf?alt=media&token=5fa5dc2a-76b6-447c-895b-4721eb283a05"
    },
    {
        "name": "M1(WME01)MS",
        "id": 5,
        "url": "https://files.gitbook.com/v0/b/gitbook-x-prod.appspot.com/o/spaces%2FwFIlpgG4w2DGcN1UNMAZ%2Fuploads%2FQrPTIJnvyhO1EhYfzLoG%2FWME01_01_msc_20150305.pdf?alt=media&token=f01ed884-ea4e-4f95-a2a9-9b3266780126"
    },
    {
        "name": "M2(WME02)MS",
        "id": 6,
        "url": "https://files.gitbook.com/v0/b/gitbook-x-prod.appspot.com/o/spaces%2FwFIlpgG4w2DGcN1UNMAZ%2Fuploads%2Fbza9gdUIiFqDTCZhBuZd%2FWME02_01_msc_20150305.pdf?alt=media&token=618a504f-c735-4fde-b842-e61ec5133b9d"
    },
    {
        "name": "M3(WME03)MS",
        "id": 7,
        "url": "https://files.gitbook.com/v0/b/gitbook-x-prod.appspot.com/o/spaces%2FwFIlpgG4w2DGcN1UNMAZ%2Fuploads%2FKO9ztqaXcJSnjviyycov%2FWME03_01_msc_20150305.pdf?alt=media&token=689c56a9-7c3b-4dc1-af78-600ba03440b7"
    },
    {
        "name": "S1(WST01)MS",
        "id": 8,
        "url": "https://files.gitbook.com/v0/b/gitbook-x-prod.appspot.com/o/spaces%2FwFIlpgG4w2DGcN1UNMAZ%2Fuploads%2FRTNgtSb5lRGgvjl3yBCI%2FWST01_01_msc_20150305.pdf?alt=media&token=fdd2da28-09aa-4e0d-a9b1-d6fe6419bd66"
    },
    {
        "name": "S2(WST02)MS",
        "id": 9,
        "url": "https://files.gitbook.com/v0/b/gitbook-x-prod.appspot.com/o/spaces%2FwFIlpgG4w2DGcN1UNMAZ%2Fuploads%2FtsBkG6W6UoM4XrLtm05f%2FWST02_01_msc_20150305.pdf?alt=media&token=78315abd-77bf-47c6-bab4-71782d9189e7"
    },
]




